{
  "text": "Meher Venkat Raman\nvenkatramanmeher@gmail.com\n+91 9059032160\nLinkedIn\nGitHub\nLeetCode\nEducation\nIntegrated MTech, Computer Science & Engineering, University of Hyderabad\nGPA: 8.8\n2022 – 2027\nSenior Secondary, CBSE, Sri Chaitanya\nPercentage: 93.8\n2020 – 2022\nProfessional Experience\nSummer Research Intern – Indian Statistical Institute (ISI),\nIndian Statistical Institute (ISI)\n• Modified the Kyber post-quantum cryptographic scheme to support multiple\ncompression (du, dv) and noise (η₁, η₂) parameters.\n• Implemented and optimized the core Kyber reference code in C for performance\nand efficiency evaluation.\n05/2025 – 07/2025\nKolkata, India\n• Built automated benchmarking tools to measure cycle counts and runtime across\nparameter variants.\n• Conducted performance analysis and verified encryption/decryption correctness\nacross all configurations.\n• GitHub: github.com/meher4567/kyber-dilithium-tweaks\nSkills\nProgramming\nPython, Java, JavaScript, C, C++, SQL\nTools & Technologies\nGit, MySQL, REST APIs, WebSockets, Kubernetes,\nDocker, CI/CD,SQLite,SageMath\nManagement\nProject Management, Agile Methodologies,\nTeamCollaboration, StrategicPlanning\nWeb & Frameworks\nReact, Django, Flask, Vite, SCSS,FastAPI,Streamlit\nConcepts\nMachine Learning, Deep Learning, NLP, Cloud\nComputing, Database\nManagement, Microservices,Post-Quantum\nCryptography,MLOps,Risk Analysis\nProjects\nAlgorithmic Trading System with Machine Learning, Course Project – Algorithms & Game Theory\n• Developed a production-ready algorithmic trading platform integrating ensemble ML models (LSTM, Random\nForest, XGBoost) for multi-stock signal generation.\n• Implemented six trading strategies and a FastAPI + Streamlit interface for live signal visualization and\nmanagement.\n• Built a Monte Carlo risk analysis module (10,000+ simulations) with advanced metrics such as Sharpe,\nSortino, and VaR.\n• Designed backtesting and portfolio optimization frameworks achieving 210+ backtests across 10+ stocks with\na 68% average win rate.\nAI Resume Analyzer (ML & NLP)\n•Built an AI-powered resume screening system using NLP and ML.\n•Extracted skills, ranked resumes, and matched job descriptions.\n•Used advanced NLP techniques for semantic job-resume matching.\n•Technologies: Python, TensorFlow, Pandas, Django.\nAirline Management System (React + Django + MySQL)\n•Developed a full-stack airline management system with admin & user functionalities.\n•Integrated CRUD APIs for managing bookings, flights, airports, and payments.\n•Implemented a role-based authentication system.\n•Technologies: React (Vite), Django, MySQL.\nAchievements\nSolved 450+ coding problems on GitHub, LeetCode & GFG.\nReceived fellowship from the University for topping the class three times.\nTop 1 percentile in Both JEE-Advanced and JEE-Mains.\nCertifications\n- Supervised Machine Learning:\nRegression and Classification -\nCoursera\n- Neural Networks and Deep\nLearning - Coursera",
  "extraction_method": "pymupdf",
  "success": true,
  "error": null,
  "metadata": {
    "num_pages": 2,
    "title": "",
    "author": "",
    "subject": "",
    "creator": "FlowCV - https://flowcv.com",
    "producer": "Skia/PDF m141",
    "created_date": "D:20251028132605+00'00'",
    "modified_date": "D:20251028132605+00'00'"
  },
  "file_name": "my_resume.pdf",
  "file_size": 73065,
  "file_type": "pdf",
  "file_path": "D:\\CKXJ\\ML\\TD1\\data\\sample_resumes\\real_world\\my_resume.pdf",
  "char_count": 2902,
  "word_count": 373,
  "sections": {
    "education": {
      "raw_header": "Education",
      "content": "Integrated MTech, Computer Science & Engineering, University of Hyderabad\nGPA: 8.8\n2022 – 2027\nSenior Secondary, CBSE, Sri Chaitanya\nPercentage: 93.8\n2020 – 2022",
      "confidence": 0.8999999999999999,
      "char_count": 161
    },
    "experience": {
      "raw_header": "Professional Experience",
      "content": "Summer Research Intern – Indian Statistical Institute (ISI),\nIndian Statistical Institute (ISI)\n• Modified the Kyber post-quantum cryptographic scheme to support multiple\ncompression (du, dv) and noise (η₁, η₂) parameters.\n• Implemented and optimized the core Kyber reference code in C for performance\nand efficiency evaluation.\n05/2025 – 07/2025\nKolkata, India\n• Built automated benchmarking tools to measure cycle counts and runtime across\nparameter variants.\n• Conducted performance analysis and verified encryption/decryption correctness\nacross all configurations.\n• GitHub: github.com/meher4567/kyber-dilithium-tweaks",
      "confidence": 0.8999999999999999,
      "char_count": 622
    },
    "skills": {
      "raw_header": "Skills",
      "content": "Programming\nPython, Java, JavaScript, C, C++, SQL\nTools & Technologies\nGit, MySQL, REST APIs, WebSockets, Kubernetes,\nDocker, CI/CD,SQLite,SageMath\nManagement\nProject Management, Agile Methodologies,\nTeamCollaboration, StrategicPlanning\nWeb & Frameworks\nReact, Django, Flask, Vite, SCSS,FastAPI,Streamlit\nConcepts\nMachine Learning, Deep Learning, NLP, Cloud\nComputing, Database\nManagement, Microservices,Post-Quantum\nCryptography,MLOps,Risk Analysis",
      "confidence": 0.8999999999999999,
      "char_count": 449
    },
    "projects": {
      "raw_header": "Projects",
      "content": "Algorithmic Trading System with Machine Learning, Course Project – Algorithms & Game Theory\n• Developed a production-ready algorithmic trading platform integrating ensemble ML models (LSTM, Random\nForest, XGBoost) for multi-stock signal generation.\n• Implemented six trading strategies and a FastAPI + Streamlit interface for live signal visualization and\nmanagement.\n• Built a Monte Carlo risk analysis module (10,000+ simulations) with advanced metrics such as Sharpe,\nSortino, and VaR.\n• Designed backtesting and portfolio optimization frameworks achieving 210+ backtests across 10+ stocks with\na 68% average win rate.\nAI Resume Analyzer (ML & NLP)\n•Built an AI-powered resume screening system using NLP and ML.\n•Extracted skills, ranked resumes, and matched job descriptions.\n•Used advanced NLP techniques for semantic job-resume matching.\n•Technologies: Python, TensorFlow, Pandas, Django.\nAirline Management System (React + Django + MySQL)\n•Developed a full-stack airline management system with admin & user functionalities.\n•Integrated CRUD APIs for managing bookings, flights, airports, and payments.\n•Implemented a role-based authentication system.\n•Technologies: React (Vite), Django, MySQL.",
      "confidence": 0.8999999999999999,
      "char_count": 1201
    },
    "achievements": {
      "raw_header": "Achievements",
      "content": "Solved 450+ coding problems on GitHub, LeetCode & GFG.\nReceived fellowship from the University for topping the class three times.\nTop 1 percentile in Both JEE-Advanced and JEE-Mains.",
      "confidence": 0.8999999999999999,
      "char_count": 182
    },
    "certifications": {
      "raw_header": "Certifications",
      "content": "- Supervised Machine Learning:\nRegression and Classification -\nCoursera\n- Neural Networks and Deep\nLearning - Coursera",
      "confidence": 0.8999999999999999,
      "char_count": 118
    }
  },
  "sections_found": [
    "education",
    "experience",
    "skills",
    "projects",
    "achievements",
    "certifications"
  ],
  "contact_info": {
    "emails": [
      "venkatramanmeher@gmail.com"
    ],
    "phones": [
      "9059032160",
      "+91 9059032160"
    ],
    "linkedin": null,
    "github": "https://github.com/meher4567",
    "website": null,
    "location": "Engineering, University"
  },
  "name": "Meher Venkat Raman",
  "name_extraction": {
    "method": "both_agree",
    "confidence": null,
    "ml_enabled": true
  },
  "skills": {
    "all_skills": [
      "Agile",
      "Airline Management System (React + Django + MySQL",
      "C++",
      "CI/CD",
      "Cloud Computing",
      "Deep Learning",
      "Django",
      "Docker",
      "FastAPI",
      "Flask",
      "Git",
      "GitHub",
      "Java",
      "JavaScript",
      "Kubernetes",
      "Machine Learning",
      "Microservices",
      "MySQL",
      "NLP",
      "Neural Networks",
      "Pandas",
      "Project Management",
      "Python",
      "REST APIs",
      "React",
      "SQL",
      "SQLite",
      "TensorFlow",
      "Tools & Technologies Git, MySQL",
      "Web & Frameworks",
      "WebSockets",
      "github"
    ],
    "by_category": {
      "technical": [
        "Airline Management System (React + Django + MySQL",
        "C++",
        "Cloud Computing",
        "Deep Learning",
        "Django",
        "FastAPI",
        "Flask",
        "Java",
        "JavaScript",
        "Machine Learning",
        "MySQL",
        "NLP",
        "Neural Networks",
        "Pandas",
        "Python",
        "REST APIs",
        "React",
        "SQL",
        "SQLite",
        "TensorFlow",
        "Tools & Technologies Git, MySQL",
        "Web & Frameworks",
        "WebSockets"
      ],
      "soft": [
        "Project Management"
      ],
      "tools": [
        "Docker",
        "Git",
        "GitHub",
        "Kubernetes",
        "github"
      ],
      "methodologies": [
        "Agile",
        "CI/CD",
        "Microservices"
      ]
    },
    "count": 32,
    "extraction_method": "dynamic_ner_pattern"
  },
  "organizations": {
    "all": [
      "University of Hyderabad",
      "Indian Statistical Institute",
      "TeamCollaboration",
      "Cloud Computing",
      "Coursera - Neural Networks",
      "Project Management",
      "Agile Methodologies",
      "LeetCode & GFG",
      "Post-Quantum Cryptography",
      "Random Forest"
    ],
    "companies": [
      "TeamCollaboration",
      "Cloud Computing",
      "Coursera - Neural Networks",
      "Project Management",
      "Agile Methodologies",
      "LeetCode & GFG"
    ],
    "universities": [
      "University of Hyderabad",
      "Indian Statistical Institute"
    ],
    "detailed": [
      {
        "name": "University of Hyderabad",
        "category": "university",
        "confidence": 1.0,
        "section": null
      },
      {
        "name": "Indian Statistical Institute",
        "category": "university",
        "confidence": 1.0,
        "section": null
      },
      {
        "name": "TeamCollaboration",
        "category": "company",
        "confidence": 1.0,
        "section": "skills"
      },
      {
        "name": "Cloud Computing",
        "category": "company",
        "confidence": 1.0,
        "section": null
      },
      {
        "name": "Coursera - Neural Networks",
        "category": "company",
        "confidence": 1.0,
        "section": null
      },
      {
        "name": "Project Management",
        "category": "company",
        "confidence": 0.95,
        "section": "skills"
      },
      {
        "name": "Agile Methodologies",
        "category": "company",
        "confidence": 0.95,
        "section": "skills"
      },
      {
        "name": "LeetCode & GFG",
        "category": "company",
        "confidence": 0.9,
        "section": null
      },
      {
        "name": "Post-Quantum Cryptography",
        "category": "institution",
        "confidence": 0.6,
        "section": null
      },
      {
        "name": "Random Forest",
        "category": "institution",
        "confidence": 0.6,
        "section": "projects"
      }
    ],
    "summary": {
      "total": 10,
      "companies": 6,
      "universities": 2,
      "institutions": 2,
      "other": 0,
      "avg_confidence": 0.9,
      "by_category": {
        "company": [
          "TeamCollaboration",
          "Cloud Computing",
          "Coursera - Neural Networks",
          "Project Management",
          "Agile Methodologies",
          "LeetCode & GFG"
        ],
        "university": [
          "University of Hyderabad",
          "Indian Statistical Institute"
        ],
        "institution": [
          "Post-Quantum Cryptography",
          "Random Forest"
        ],
        "other": []
      }
    },
    "extraction_method": "ner_ml"
  },
  "quality": {
    "overall_score": 95.0,
    "extraction_quality": 100.0,
    "completeness": 90.0,
    "formatting_quality": 90.0,
    "readability": 100.0,
    "is_scanned": false,
    "has_images": false,
    "issues": [
      "Missing professional summary",
      "Resume is too lengthy"
    ],
    "recommendations": [
      "Consider adding a professional summary",
      "Consider condensing to 1-2 pages"
    ]
  }
}